rasa_sdk/__init__.py
rasa_sdk/__main__.py
rasa_sdk/cli/__init__.py
rasa_sdk/cli/arguments.py
rasa_sdk/constants.py
rasa_sdk/endpoint.py
rasa_sdk/events.py
rasa_sdk/exceptions.py
rasa_sdk/executor.py
rasa_sdk/forms.py
rasa_sdk/grpc_errors.py
rasa_sdk/grpc_py/__init__.py
rasa_sdk/grpc_py/action_webhook_pb2.py
rasa_sdk/grpc_py/action_webhook_pb2.pyi
rasa_sdk/grpc_py/action_webhook_pb2_grpc.py
rasa_sdk/grpc_server.py
rasa_sdk/interfaces.py
rasa_sdk/knowledge_base/__init__.py
rasa_sdk/knowledge_base/actions.py
rasa_sdk/knowledge_base/storage.py
rasa_sdk/knowledge_base/utils.py
rasa_sdk/plugin.py
rasa_sdk/slots.py
rasa_sdk/tracing/config.py
rasa_sdk/tracing/endpoints.py
rasa_sdk/tracing/instrumentation/attribute_extractors.py
rasa_sdk/tracing/instrumentation/instrumentation.py
rasa_sdk/tracing/tracer_register.py
rasa_sdk/tracing/utils.py
rasa_sdk/types.py
rasa_sdk/utils.py
rasa_sdk/version.py
rasa_sdk-3.14.0.dist-info/LICENSE.txt
rasa_sdk-3.14.0.dist-info/METADATA
rasa_sdk-3.14.0.dist-info/WHEEL
rasa_sdk-3.14.0.dist-info/RECORD
