Metadata-Version: 2.3
Name: rasa-sdk
Version: 3.14.0
Summary: Open source machine learning framework to automate text- and voice-based conversations: NLU, dialogue management, connect to Slack, Facebook, and more - Create chatbots and voice assistants
License: Apache-2.0
Keywords: nlp,machine-learning,machine-learning-library,bot,bots,botkit,rasa conversational-agents,conversational-ai,chatbot,chatbot-framework,bot-framework
Author: Rasa Technologies GmbH
Author-email: hi@rasa.com
Maintainer: Tom Bocklisch
Maintainer-email: tom@rasa.com
Requires-Python: >3.9,<3.14
Classifier: Development Status :: 5 - Production/Stable
Classifier: Intended Audience :: Developers
Classifier: License :: OSI Approved :: Apache Software License
Classifier: Programming Language :: Python :: 3
Classifier: Programming Language :: Python :: 3.10
Classifier: Programming Language :: Python :: 3.11
Classifier: Programming Language :: Python :: 3.12
Classifier: Programming Language :: Python :: 3.13
Classifier: Topic :: Software Development :: Libraries
Requires-Dist: Sanic-Cors (>=2.0.0,<3.0.0)
Requires-Dist: coloredlogs (>=10,<16)
Requires-Dist: grpcio (>=1.66.2,<1.67.0)
Requires-Dist: grpcio-health-checking (>=1.59.3,<1.60.0)
Requires-Dist: grpcio-tools (>=1.66.2,<1.67.0)
Requires-Dist: opentelemetry-api (>=1.33.0,<1.34.0)
Requires-Dist: opentelemetry-exporter-otlp (>=1.33.0,<1.34.0)
Requires-Dist: opentelemetry-sdk (>=1.33.0,<1.34.0)
Requires-Dist: pluggy (>=1.0.0,<2.0.0)
Requires-Dist: protobuf (>=5.29.5,<5.30.0)
Requires-Dist: pydantic (>=2.6.4,<3.0.0)
Requires-Dist: ruamel.yaml (>=0.16.5,<0.18.0)
Requires-Dist: sanic (>=22.12,<23.0)
Requires-Dist: typing-extensions (>=4.1.1,<5.0.0)
Requires-Dist: websockets (>=10.0,<12.0)
Project-URL: Documentation, https://rasa.com/docs
Project-URL: Homepage, https://rasa.com
Project-URL: Repository, https://github.com/rasahq/rasa-sdk
